agent_framework_mem0/__init__.py
agent_framework_mem0/_provider.py
agent_framework_mem0-1.0.0b260130.dist-info/licenses/LICENSE
agent_framework_mem0-1.0.0b260130.dist-info/WHEEL
agent_framework_mem0-1.0.0b260130.dist-info/METADATA
agent_framework_mem0-1.0.0b260130.dist-info/RECORD
